vorp/__init__.py
vorp/constants.json
vorp/main.py
vorp/rag.py
vorp/tools.py
vorp-0.1.11.dist-info/METADATA
vorp-0.1.11.dist-info/WHEEL
vorp-0.1.11.dist-info/entry_points.txt
vorp-0.1.11.dist-info/top_level.txt
vorp-0.1.11.dist-info/RECORD
