Metadata-Version: 2.4
Name: vorp
Version: 0.1.11
Summary: A terminal-based AI companion.
Author-email: Siddharth Bayapureddy <siddharthbayapureddy@gmail.com>
License: MIT
Project-URL: Homepage, https://github.com/SiddharthBayapureddy/vorp
Project-URL: Repository, https://github.com/SiddharthBayapureddy/vorp.git
Project-URL: Issues, https://github.com/SiddharthBayapureddy/vorp/issues
Project-URL: Source Code, https://github.com/SiddharthBayapureddy/vorp
Keywords: ai,llm,cli,terminal,assistant,rag,chatbot,developer-tools
Classifier: Development Status :: 3 - Alpha
Classifier: Environment :: Console
Classifier: Intended Audience :: Developers
Classifier: License :: OSI Approved :: MIT License
Classifier: Operating System :: OS Independent
Classifier: Programming Language :: Python :: 3
Classifier: Programming Language :: Python :: 3.10
Classifier: Programming Language :: Python :: 3.11
Classifier: Programming Language :: Python :: 3.12
Classifier: Topic :: Software Development :: Libraries :: Python Modules
Classifier: Topic :: Communications :: Chat
Classifier: Topic :: Terminals
Requires-Python: >=3.10
Requires-Dist: chromadb>=0.4.22
Requires-Dist: litellm>=1.0.0
Requires-Dist: python-dotenv>=1.0.0
Requires-Dist: requests>=2.31.0
Requires-Dist: rich>=13.0.0
Requires-Dist: typer>=0.9.0
Requires-Dist: pydantic>=2.0.0
